pprint/__init__.py
pprint/main.py
gbq_tools-0.0.1.dist-info/METADATA
gbq_tools-0.0.1.dist-info/WHEEL
gbq_tools-0.0.1.dist-info/licenses/LICENSE
gbq_tools-0.0.1.dist-info/RECORD
