Metadata-Version: 2.1
Name: gbq-tools
Version: 0.0.1
Summary: Dependency Confusion PoC
Author-email: Felix <flx1101@aboutyou.com>
License:                     GNU GENERAL PUBLIC LICENSE
Classifier: License :: OSI Approved :: MIT License
Classifier: Operating System :: OS Independent
Classifier: Programming Language :: Python :: 3
Requires-Python: >=3.7
